LICENSE
README.md
VERSION
requirements.txt
setup.py
texta_parsers/__init__.py
texta_parsers/doc_parser.py
texta_parsers/email_parser.py
texta_parsers/exceptions.py
texta_parsers/settings.py
texta_parsers.egg-info/PKG-INFO
texta_parsers.egg-info/SOURCES.txt
texta_parsers.egg-info/dependency_links.txt
texta_parsers.egg-info/requires.txt
texta_parsers.egg-info/top_level.txt
texta_parsers/tools/__init__.py
texta_parsers/tools/archive.py
texta_parsers/tools/elastic.py
texta_parsers/tools/extension.py
texta_parsers/tools/message.py
texta_parsers/tools/meta_extractor.py
texta_parsers/tools/mlp_processor.py
texta_parsers/tools/pst_extractor.py
texta_parsers/tools/rar_extractor.py
texta_parsers/tools/scanner.py
texta_parsers/tools/tar_extractor.py
texta_parsers/tools/utils.py