Metadata-Version: 2.1
Name: texta-parsers
Version: 3.0.0
Summary: texta-parsers
Author: TEXTA
Author-email: info@texta.ee
License: GPLv3
Provides-Extra: mlp
License-File: LICENSE
